odoo10_addon_pos_session_pay_invoice-10.0.1.0.0-py2.7-nspkg.pth
odoo/addons/pos_session_pay_invoice/README.rst
odoo/addons/pos_session_pay_invoice/__init__.py
odoo/addons/pos_session_pay_invoice/__manifest__.py
odoo/addons/pos_session_pay_invoice/static/description/icon.png
odoo/addons/pos_session_pay_invoice/tests/__init__.py
odoo/addons/pos_session_pay_invoice/tests/test_pay_invoice.py
odoo/addons/pos_session_pay_invoice/views/account_bank_statement.xml
odoo/addons/pos_session_pay_invoice/views/pos_session.xml
odoo/addons/pos_session_pay_invoice/wizard/__init__.py
odoo/addons/pos_session_pay_invoice/wizard/cash_invoice_in.py
odoo/addons/pos_session_pay_invoice/wizard/cash_invoice_in.xml
odoo/addons/pos_session_pay_invoice/wizard/cash_invoice_out.py
odoo/addons/pos_session_pay_invoice/wizard/cash_invoice_out.xml
odoo10_addon_pos_session_pay_invoice-10.0.1.0.0.dist-info/DESCRIPTION.rst
odoo10_addon_pos_session_pay_invoice-10.0.1.0.0.dist-info/METADATA
odoo10_addon_pos_session_pay_invoice-10.0.1.0.0.dist-info/RECORD
odoo10_addon_pos_session_pay_invoice-10.0.1.0.0.dist-info/WHEEL
odoo10_addon_pos_session_pay_invoice-10.0.1.0.0.dist-info/metadata.json
odoo10_addon_pos_session_pay_invoice-10.0.1.0.0.dist-info/namespace_packages.txt
odoo10_addon_pos_session_pay_invoice-10.0.1.0.0.dist-info/top_level.txt
